lerg/RG_explainers.py
lerg/__init__.py
lerg/metrics.py
lerg/perturbation_models.py
lerg/visualize.py
lerg-0.0.1.dist-info/LICENSE
lerg-0.0.1.dist-info/METADATA
lerg-0.0.1.dist-info/WHEEL
lerg-0.0.1.dist-info/top_level.txt
lerg-0.0.1.dist-info/RECORD
